{
"instructions_readme": "1) Open Chrome, 2) go to chrome://tracing, 3) click Load, 4) navigate to this file.",

"traceEvents":[
{ "pid": 1, "tid": 1, "ph": "M", "name": "thread_name", "args": { "name": "" } },
{ "pid": 1, "tid": 1, "ts": 633.5999965667725, "dur": 6681381.8359375, "ph": "X", "name": "il2cpp.exe", "args": { "durationMS": 6681.3818359375, "detail": "" } },
{ "pid": 1, "tid": 1, "ts": 23448.898315429688, "dur": 6657509.765625, "ph": "X", "name": "Build", "args": { "durationMS": 6657.509765625, "detail": "" } },
{ "pid": 1, "tid": 1, "ts": 28538.700103759766, "dur": 6651428.7109375, "ph": "X", "name": "BuildBinary", "args": { "durationMS": 6651.4287109375, "detail": "" } },
{ "pid": 1, "tid": 1, "ts": 28816.499710083008, "dur": 70652.60314941406, "ph": "X", "name": "FindFilesToCompile", "args": { "durationMS": 70.65260314941406, "detail": "" } },
{ "pid": 1, "tid": 1, "ts": 99565.49835205078, "dur": 66469.39849853516, "ph": "X", "name": "Calculate header hashes", "args": { "durationMS": 66.46939849853516, "detail": "" } },
{ "pid": 1, "tid": 1, "ts": 166035.5987548828, "dur": 13098.799705505371, "ph": "X", "name": "Calculate lumped hashes", "args": { "durationMS": 13.098799705505371, "detail": "" } },
{ "pid": 1, "tid": 1, "ts": 179217.2088623047, "dur": 1309722.0458984375, "ph": "X", "name": "BuildAllCppFiles", "args": { "durationMS": 1309.7220458984375, "detail": "" } },
{ "pid": 1, "tid": 1, "ts": 183057.89184570312, "dur": 1305880.615234375, "ph": "X", "name": "Compile", "args": { "durationMS": 1305.880615234375, "detail": "" } },
{ "pid": 1, "tid": 1, "ts": 1488951.904296875, "dur": 421.00000381469727, "ph": "X", "name": "OnBeforeLink Build", "args": { "durationMS": 0.42100000381469727, "detail": "" } },
{ "pid": 1, "tid": 1, "ts": 1489372.9248046875, "dur": 5084081.0546875, "ph": "X", "name": "Postprocess Object Files", "args": { "durationMS": 5084.0810546875, "detail": "" } },
{ "pid": 1, "tid": 1, "ts": 1490980.3466796875, "dur": 5082472.65625, "ph": "X", "name": "Link", "args": { "durationMS": 5082.47265625, "detail": "libil2cpp.so" } },
{ "pid": 1, "tid": 1, "ts": 1501765.380859375, "dur": 10826.99966430664, "ph": "X", "name": "hash linker invocation", "args": { "durationMS": 10.82699966430664, "detail": "" } },
{ "pid": 1, "tid": 1, "ts": 1517803.22265625, "dur": 4296993.65234375, "ph": "X", "name": "ActualLinkerInvocation", "args": { "durationMS": 4296.99365234375, "detail": "libil2cpp.so" } },
{ "pid": 1, "tid": 1, "ts": 5815070.80078125, "dur": 639252.5024414062, "ph": "X", "name": "ToolChain OnAfterLink Build", "args": { "durationMS": 639.2525024414062, "detail": "" } },
{ "pid": 1, "tid": 1, "ts": 5819228.02734375, "dur": 109344.39849853516, "ph": "X", "name": "strip", "args": { "durationMS": 109.34439849853516, "detail": "" } },
{ "pid": 1, "tid": 1, "ts": 5928641.11328125, "dur": 240588.10424804688, "ph": "X", "name": "strip", "args": { "durationMS": 240.58810424804688, "detail": "debug" } },
{ "pid": 1, "tid": 1, "ts": 6169537.109375, "dur": 284783.99658203125, "ph": "X", "name": "strip", "args": { "durationMS": 284.78399658203125, "detail": "debug link" } },
{ "pid": 1, "tid": 1, "ts": 6573454.58984375, "dur": 66210.60180664062, "ph": "X", "name": "ProgramDescription Finalize Build", "args": { "durationMS": 66.21060180664062, "detail": "" } },
{ "pid": 1, "tid": 1, "ts": 6639665.52734375, "dur": 40301.5022277832, "ph": "X", "name": "Clean IL2CPP Cache", "args": { "durationMS": 40.3015022277832, "detail": "" } },
{ "pid": 1, "tid": 13, "ph": "M", "name": "thread_name", "args": { "name": "" } },
{ "pid": 1, "tid": 13, "ts": 138759.90295410156, "dur": 5496.699810028076, "ph": "X", "name": "FileHashProvider.Initialize", "args": { "durationMS": 5.496699810028076, "detail": "." } },
{ "pid": 1, "tid": 13, "ts": 139944.80895996094, "dur": 3123.6000061035156, "ph": "X", "name": "HashOfAllFilesWithProviderExtensionInDirectory", "args": { "durationMS": 3.1236000061035156, "detail": ".h ." } },
{ "pid": 1, "tid": 13, "ts": 143079.7882080078, "dur": 1175.7999658584595, "ph": "X", "name": "HashOfAllFilesWithProviderExtensionInDirectory", "args": { "durationMS": 1.1757999658584595, "detail": ".inc ." } },
{ "pid": 1, "tid": 5, "ph": "M", "name": "thread_name", "args": { "name": "" } },
{ "pid": 1, "tid": 5, "ts": 138776.2908935547, "dur": 14714.899063110352, "ph": "X", "name": "FileHashProvider.Initialize", "args": { "durationMS": 14.714899063110352, "detail": "C:\\Program Files\\Unity\\Hub\\Editor\\2020.3.6f1\\Editor\\Data\\il2cpp\\external\\baselib\\Include" } },
{ "pid": 1, "tid": 5, "ts": 139946.7010498047, "dur": 12548.700332641602, "ph": "X", "name": "HashOfAllFilesWithProviderExtensionInDirectory", "args": { "durationMS": 12.548700332641602, "detail": ".h C:\\Program Files\\Unity\\Hub\\Editor\\2020.3.6f1\\Editor\\Data\\il2cpp\\external\\baselib\\Include" } },
{ "pid": 1, "tid": 5, "ts": 152499.29809570312, "dur": 975.0000238418579, "ph": "X", "name": "HashOfAllFilesWithProviderExtensionInDirectory", "args": { "durationMS": 0.9750000238418579, "detail": ".inc C:\\Program Files\\Unity\\Hub\\Editor\\2020.3.6f1\\Editor\\Data\\il2cpp\\external\\baselib\\Include" } },
{ "pid": 1, "tid": 6, "ph": "M", "name": "thread_name", "args": { "name": "" } },
{ "pid": 1, "tid": 6, "ts": 138794.09790039062, "dur": 13156.000137329102, "ph": "X", "name": "FileHashProvider.Initialize", "args": { "durationMS": 13.156000137329102, "detail": "C:\\Program Files\\Unity\\Hub\\Editor\\2020.3.6f1\\Editor\\Data\\il2cpp\\external\\baselib\\Platforms\\Android\\Include" } },
{ "pid": 1, "tid": 6, "ts": 139953.09448242188, "dur": 9930.19962310791, "ph": "X", "name": "HashOfAllFilesWithProviderExtensionInDirectory", "args": { "durationMS": 9.93019962310791, "detail": ".h C:\\Program Files\\Unity\\Hub\\Editor\\2020.3.6f1\\Editor\\Data\\il2cpp\\external\\baselib\\Platforms\\Android\\Include" } },
{ "pid": 1, "tid": 6, "ts": 149890.10620117188, "dur": 2057.8999519348145, "ph": "X", "name": "HashOfAllFilesWithProviderExtensionInDirectory", "args": { "durationMS": 2.0578999519348145, "detail": ".inc C:\\Program Files\\Unity\\Hub\\Editor\\2020.3.6f1\\Editor\\Data\\il2cpp\\external\\baselib\\Platforms\\Android\\Include" } },
{ "pid": 1, "tid": 7, "ph": "M", "name": "thread_name", "args": { "name": "" } },
{ "pid": 1, "tid": 7, "ts": 138796.5087890625, "dur": 13256.799697875977, "ph": "X", "name": "FileHashProvider.Initialize", "args": { "durationMS": 13.256799697875977, "detail": "C:\\Program Files\\Unity\\Hub\\Editor\\2020.3.6f1\\Editor\\Data\\il2cpp\\external\\bdwgc\\include" } },
{ "pid": 1, "tid": 7, "ts": 139951.50756835938, "dur": 11508.099555969238, "ph": "X", "name": "HashOfAllFilesWithProviderExtensionInDirectory", "args": { "durationMS": 11.508099555969238, "detail": ".h C:\\Program Files\\Unity\\Hub\\Editor\\2020.3.6f1\\Editor\\Data\\il2cpp\\external\\bdwgc\\include" } },
{ "pid": 1, "tid": 7, "ts": 151475.09765625, "dur": 573.8999843597412, "ph": "X", "name": "HashOfAllFilesWithProviderExtensionInDirectory", "args": { "durationMS": 0.5738999843597412, "detail": ".inc C:\\Program Files\\Unity\\Hub\\Editor\\2020.3.6f1\\Editor\\Data\\il2cpp\\external\\bdwgc\\include" } },
{ "pid": 1, "tid": 8, "ph": "M", "name": "thread_name", "args": { "name": "" } },
{ "pid": 1, "tid": 8, "ts": 138798.9959716797, "dur": 13406.100273132324, "ph": "X", "name": "FileHashProvider.Initialize", "args": { "durationMS": 13.406100273132324, "detail": "C:\\Program Files\\Unity\\Hub\\Editor\\2020.3.6f1\\Editor\\Data\\il2cpp\\external\\bdwgc\\libatomic_ops\\src" } },
{ "pid": 1, "tid": 8, "ts": 139955.30700683594, "dur": 11437.000274658203, "ph": "X", "name": "HashOfAllFilesWithProviderExtensionInDirectory", "args": { "durationMS": 11.437000274658203, "detail": ".h C:\\Program Files\\Unity\\Hub\\Editor\\2020.3.6f1\\Editor\\Data\\il2cpp\\external\\bdwgc\\libatomic_ops\\src" } },
{ "pid": 1, "tid": 8, "ts": 151397.79663085938, "dur": 800.7000088691711, "ph": "X", "name": "HashOfAllFilesWithProviderExtensionInDirectory", "args": { "durationMS": 0.8007000088691711, "detail": ".inc C:\\Program Files\\Unity\\Hub\\Editor\\2020.3.6f1\\Editor\\Data\\il2cpp\\external\\bdwgc\\libatomic_ops\\src" } },
{ "pid": 1, "tid": 12, "ph": "M", "name": "thread_name", "args": { "name": "" } },
{ "pid": 1, "tid": 12, "ts": 138804.0008544922, "dur": 5068.900108337402, "ph": "X", "name": "FileHashProvider.Initialize", "args": { "durationMS": 5.068900108337402, "detail": "C:\\Users\\MSI\\Documents\\GitHub\\Sample\\Engine\\Library\\Il2cppBuildCache\\Android\\armeabi-v7a\\il2cppOutput" } },
{ "pid": 1, "tid": 12, "ts": 139960.60180664062, "dur": 3107.100009918213, "ph": "X", "name": "HashOfAllFilesWithProviderExtensionInDirectory", "args": { "durationMS": 3.107100009918213, "detail": ".h C:\\Users\\MSI\\Documents\\GitHub\\Sample\\Engine\\Library\\Il2cppBuildCache\\Android\\armeabi-v7a\\il2cppOutput" } },
{ "pid": 1, "tid": 12, "ts": 143080.29174804688, "dur": 789.6999716758728, "ph": "X", "name": "HashOfAllFilesWithProviderExtensionInDirectory", "args": { "durationMS": 0.7896999716758728, "detail": ".inc C:\\Users\\MSI\\Documents\\GitHub\\Sample\\Engine\\Library\\Il2cppBuildCache\\Android\\armeabi-v7a\\il2cppOutput" } },
{ "pid": 1, "tid": 11, "ph": "M", "name": "thread_name", "args": { "name": "" } },
{ "pid": 1, "tid": 11, "ts": 138805.80139160156, "dur": 11442.79956817627, "ph": "X", "name": "FileHashProvider.Initialize", "args": { "durationMS": 11.44279956817627, "detail": "C:\\Program Files\\Unity\\Hub\\Editor\\2020.3.6f1\\Editor\\Data\\il2cpp\\libil2cpp\\pch" } },
{ "pid": 1, "tid": 11, "ts": 139961.70043945312, "dur": 8121.299743652344, "ph": "X", "name": "HashOfAllFilesWithProviderExtensionInDirectory", "args": { "durationMS": 8.121299743652344, "detail": ".h C:\\Program Files\\Unity\\Hub\\Editor\\2020.3.6f1\\Editor\\Data\\il2cpp\\libil2cpp\\pch" } },
{ "pid": 1, "tid": 11, "ts": 148091.30859375, "dur": 2155.8001041412354, "ph": "X", "name": "HashOfAllFilesWithProviderExtensionInDirectory", "args": { "durationMS": 2.1558001041412354, "detail": ".inc C:\\Program Files\\Unity\\Hub\\Editor\\2020.3.6f1\\Editor\\Data\\il2cpp\\libil2cpp\\pch" } },
{ "pid": 1, "tid": 10, "ph": "M", "name": "thread_name", "args": { "name": "" } },
{ "pid": 1, "tid": 10, "ts": 138815.5975341797, "dur": 27176.799774169922, "ph": "X", "name": "FileHashProvider.Initialize", "args": { "durationMS": 27.176799774169922, "detail": "C:\\Program Files\\Unity\\Hub\\Editor\\2020.3.6f1\\Editor\\Data\\il2cpp\\libil2cpp" } },
{ "pid": 1, "tid": 10, "ts": 139965.6982421875, "dur": 23598.600387573242, "ph": "X", "name": "HashOfAllFilesWithProviderExtensionInDirectory", "args": { "durationMS": 23.598600387573242, "detail": ".h C:\\Program Files\\Unity\\Hub\\Editor\\2020.3.6f1\\Editor\\Data\\il2cpp\\libil2cpp" } },
{ "pid": 1, "tid": 10, "ts": 163569.80895996094, "dur": 2402.1999835968018, "ph": "X", "name": "HashOfAllFilesWithProviderExtensionInDirectory", "args": { "durationMS": 2.4021999835968018, "detail": ".inc C:\\Program Files\\Unity\\Hub\\Editor\\2020.3.6f1\\Editor\\Data\\il2cpp\\libil2cpp" } },
{ "pid": 1, "tid": 9, "ph": "M", "name": "thread_name", "args": { "name": "" } },
{ "pid": 1, "tid": 9, "ts": 138822.11303710938, "dur": 11145.999908447266, "ph": "X", "name": "FileHashProvider.Initialize", "args": { "durationMS": 11.145999908447266, "detail": "C:\\Program Files\\Unity\\Hub\\Editor\\2020.3.6f1\\Editor\\Data\\il2cpp\\external\\xxHash" } },
{ "pid": 1, "tid": 9, "ts": 139944.7021484375, "dur": 8176.400184631348, "ph": "X", "name": "HashOfAllFilesWithProviderExtensionInDirectory", "args": { "durationMS": 8.176400184631348, "detail": ".h C:\\Program Files\\Unity\\Hub\\Editor\\2020.3.6f1\\Editor\\Data\\il2cpp\\external\\xxHash" } },
{ "pid": 1, "tid": 9, "ts": 148125.70190429688, "dur": 1840.000033378601, "ph": "X", "name": "HashOfAllFilesWithProviderExtensionInDirectory", "args": { "durationMS": 1.840000033378601, "detail": ".inc C:\\Program Files\\Unity\\Hub\\Editor\\2020.3.6f1\\Editor\\Data\\il2cpp\\external\\xxHash" } },
{ "pid": 1, "tid": 32, "ph": "M", "name": "thread_name", "args": { "name": "" } },
{ "pid": 1, "tid": 32, "ts": 142948.1964111328, "dur": 4891.7999267578125, "ph": "X", "name": "HashOfFile", "args": { "durationMS": 4.8917999267578125, "detail": "C:\\Program Files\\Unity\\Hub\\Editor\\2020.3.6f1\\Editor\\Data\\il2cpp\\external\\xxHash\\xxhash.h" } },
{ "pid": 1, "tid": 20, "ph": "M", "name": "thread_name", "args": { "name": "" } },
{ "pid": 1, "tid": 20, "ts": 142949.9969482422, "dur": 4928.800106048584, "ph": "X", "name": "HashOfFile", "args": { "durationMS": 4.928800106048584, "detail": "C:\\Program Files\\Unity\\Hub\\Editor\\2020.3.6f1\\Editor\\Data\\il2cpp\\external\\bdwgc\\libatomic_ops\\src\\atomic_ops.h" } },
{ "pid": 1, "tid": 20, "ts": 147894.6075439453, "dur": 423.799991607666, "ph": "X", "name": "HashOfFile", "args": { "durationMS": 0.423799991607666, "detail": "C:\\Program Files\\Unity\\Hub\\Editor\\2020.3.6f1\\Editor\\Data\\il2cpp\\external\\bdwgc\\libatomic_ops\\src\\atomic_ops\\generalize-small.h" } },
{ "pid": 1, "tid": 19, "ph": "M", "name": "thread_name", "args": { "name": "" } },
{ "pid": 1, "tid": 19, "ts": 142986.2060546875, "dur": 4892.899990081787, "ph": "X", "name": "HashOfFile", "args": { "durationMS": 4.892899990081787, "detail": "C:\\Program Files\\Unity\\Hub\\Editor\\2020.3.6f1\\Editor\\Data\\il2cpp\\external\\bdwgc\\include\\cord_pos.h" } },
{ "pid": 1, "tid": 19, "ts": 149862.39624023438, "dur": 499.00001287460327, "ph": "X", "name": "HashOfFile", "args": { "durationMS": 0.49900001287460327, "detail": "C:\\Program Files\\Unity\\Hub\\Editor\\2020.3.6f1\\Editor\\Data\\il2cpp\\external\\bdwgc\\include\\private\\gc_priv.h" } },
{ "pid": 1, "tid": 19, "ts": 150525.1922607422, "dur": 551.9999861717224, "ph": "X", "name": "HashOfFile", "args": { "durationMS": 0.5519999861717224, "detail": "C:\\Program Files\\Unity\\Hub\\Editor\\2020.3.6f1\\Editor\\Data\\il2cpp\\external\\bdwgc\\include\\private\\thread_local_alloc.h" } },
{ "pid": 1, "tid": 29, "ph": "M", "name": "thread_name", "args": { "name": "" } },
{ "pid": 1, "tid": 29, "ts": 142976.50146484375, "dur": 4876.5997886657715, "ph": "X", "name": "HashOfFile", "args": { "durationMS": 4.8765997886657715, "detail": "C:\\Program Files\\Unity\\Hub\\Editor\\2020.3.6f1\\Editor\\Data\\il2cpp\\external\\baselib\\Include\\Baselib.h" } },
{ "pid": 1, "tid": 18, "ph": "M", "name": "thread_name", "args": { "name": "" } },
{ "pid": 1, "tid": 18, "ts": 142983.00170898438, "dur": 4870.999813079834, "ph": "X", "name": "HashOfFile", "args": { "durationMS": 4.870999813079834, "detail": "C:\\Program Files\\Unity\\Hub\\Editor\\2020.3.6f1\\Editor\\Data\\il2cpp\\external\\bdwgc\\include\\cord.h" } },
{ "pid": 1, "tid": 18, "ts": 148445.80078125, "dur": 408.60000252723694, "ph": "X", "name": "HashOfFile", "args": { "durationMS": 0.40860000252723694, "detail": "C:\\Program Files\\Unity\\Hub\\Editor\\2020.3.6f1\\Editor\\Data\\il2cpp\\external\\bdwgc\\include\\gc.h" } },
{ "pid": 1, "tid": 18, "ts": 148855.712890625, "dur": 435.49999594688416, "ph": "X", "name": "HashOfFile", "args": { "durationMS": 0.43549999594688416, "detail": "C:\\Program Files\\Unity\\Hub\\Editor\\2020.3.6f1\\Editor\\Data\\il2cpp\\external\\bdwgc\\include\\gc_cpp.h" } },
{ "pid": 1, "tid": 18, "ts": 149932.60192871094, "dur": 420.7000136375427, "ph": "X", "name": "HashOfFile", "args": { "durationMS": 0.4207000136375427, "detail": "C:\\Program Files\\Unity\\Hub\\Editor\\2020.3.6f1\\Editor\\Data\\il2cpp\\external\\bdwgc\\include\\private\\gcconfig.h" } },
{ "pid": 1, "tid": 17, "ph": "M", "name": "thread_name", "args": { "name": "" } },
{ "pid": 1, "tid": 17, "ts": 142989.7003173828, "dur": 4850.299835205078, "ph": "X", "name": "HashOfFile", "args": { "durationMS": 4.850299835205078, "detail": "C:\\Program Files\\Unity\\Hub\\Editor\\2020.3.6f1\\Editor\\Data\\il2cpp\\external\\baselib\\Platforms\\Android\\Include\\BaselibPlatformSpecificEnvironment.h" } },
{ "pid": 1, "tid": 21, "ph": "M", "name": "thread_name", "args": { "name": "" } },
{ "pid": 1, "tid": 21, "ts": 143012.10021972656, "dur": 4830.399990081787, "ph": "X", "name": "HashOfFile", "args": { "durationMS": 4.830399990081787, "detail": "C:\\Program Files\\Unity\\Hub\\Editor\\2020.3.6f1\\Editor\\Data\\il2cpp\\external\\bdwgc\\libatomic_ops\\src\\atomic_ops\\ao_version.h" } },
{ "pid": 1, "tid": 21, "ts": 147851.806640625, "dur": 552.1000027656555, "ph": "X", "name": "HashOfFile", "args": { "durationMS": 0.5521000027656555, "detail": "C:\\Program Files\\Unity\\Hub\\Editor\\2020.3.6f1\\Editor\\Data\\il2cpp\\external\\bdwgc\\libatomic_ops\\src\\atomic_ops\\generalize-arithm.h" } },
{ "pid": 1, "tid": 25, "ph": "M", "name": "thread_name", "args": { "name": "" } },
{ "pid": 1, "tid": 25, "ts": 143016.7999267578, "dur": 4823.200225830078, "ph": "X", "name": "HashOfFile", "args": { "durationMS": 4.823200225830078, "detail": "C:\\Program Files\\Unity\\Hub\\Editor\\2020.3.6f1\\Editor\\Data\\il2cpp\\libil2cpp\\pch\\pch-c.h" } },
{ "pid": 1, "tid": 30, "ph": "M", "name": "thread_name", "args": { "name": "" } },
{ "pid": 1, "tid": 30, "ts": 143027.9998779297, "dur": 4852.0002365112305, "ph": "X", "name": "HashOfFile", "args": { "durationMS": 4.8520002365112305, "detail": "C:\\Program Files\\Unity\\Hub\\Editor\\2020.3.6f1\\Editor\\Data\\il2cpp\\external\\baselib\\Include\\C\\Baselib_Alignment.h" } },
{ "pid": 1, "tid": 31, "ph": "M", "name": "thread_name", "args": { "name": "" } },
{ "pid": 1, "tid": 31, "ts": 143038.29956054688, "dur": 4801.799774169922, "ph": "X", "name": "HashOfFile", "args": { "durationMS": 4.801799774169922, "detail": "C:\\Program Files\\Unity\\Hub\\Editor\\2020.3.6f1\\Editor\\Data\\il2cpp\\external\\xxHash\\xxh3.h" } },
{ "pid": 1, "tid": 22, "ph": "M", "name": "thread_name", "args": { "name": "" } },
{ "pid": 1, "tid": 22, "ts": 143041.59545898438, "dur": 4798.500061035156, "ph": "X", "name": "HashOfFile", "args": { "durationMS": 4.798500061035156, "detail": "C:\\Program Files\\Unity\\Hub\\Editor\\2020.3.6f1\\Editor\\Data\\il2cpp\\external\\baselib\\Platforms\\Android\\Include\\C\\Baselib_ErrorState.inl.h" } },
{ "pid": 1, "tid": 41, "ph": "M", "name": "thread_name", "args": { "name": "" } },
{ "pid": 1, "tid": 41, "ts": 152617.00439453125, "dur": 341.50001406669617, "ph": "X", "name": "HashOfFile", "args": { "durationMS": 0.34150001406669617, "detail": "C:\\Program Files\\Unity\\Hub\\Editor\\2020.3.6f1\\Editor\\Data\\il2cpp\\libil2cpp\\icalls\\mscorlib\\Mono\\RuntimeMarshal.h" } },
{ "pid": 1, "tid": 41, "ts": 153287.7960205078, "dur": 1335.7000350952148, "ph": "X", "name": "HashOfFile", "args": { "durationMS": 1.3357000350952148, "detail": "C:\\Program Files\\Unity\\Hub\\Editor\\2020.3.6f1\\Editor\\Data\\il2cpp\\libil2cpp\\icalls\\mscorlib\\System.Globalization\\Generated\\CultureInfoTablesNet_4_0.h" } },
{ "pid": 1, "tid": 42, "ph": "M", "name": "thread_name", "args": { "name": "" } },
{ "pid": 1, "tid": 42, "ts": 152609.89379882812, "dur": 349.5999872684479, "ph": "X", "name": "HashOfFile", "args": { "durationMS": 0.3495999872684479, "detail": "C:\\Program Files\\Unity\\Hub\\Editor\\2020.3.6f1\\Editor\\Data\\il2cpp\\libil2cpp\\icalls\\mscorlib\\Mono\\RuntimeGPtrArrayHandle.h" } },
{ "pid": 1, "tid": 42, "ts": 156673.7060546875, "dur": 607.1000099182129, "ph": "X", "name": "HashOfFile", "args": { "durationMS": 0.6071000099182129, "detail": "C:\\Program Files\\Unity\\Hub\\Editor\\2020.3.6f1\\Editor\\Data\\il2cpp\\libil2cpp\\il2cpp-normalization-tables.h" } },
{ "pid": 1, "tid": 53, "ph": "M", "name": "thread_name", "args": { "name": "" } },
{ "pid": 1, "tid": 53, "ts": 166758.40759277344, "dur": 8541.099548339844, "ph": "X", "name": "FileHashProvider.Initialize", "args": { "durationMS": 8.541099548339844, "detail": "C:\\Program Files\\Unity\\Hub\\Editor\\2020.3.6f1\\Editor\\Data\\il2cpp\\external\\bdwgc" } },
{ "pid": 1, "tid": 53, "ts": 166784.69848632812, "dur": 1707.900047302246, "ph": "X", "name": "HashOfAllFilesWithProviderExtensionInDirectory", "args": { "durationMS": 1.707900047302246, "detail": ".cpp C:\\Program Files\\Unity\\Hub\\Editor\\2020.3.6f1\\Editor\\Data\\il2cpp\\external\\bdwgc" } },
{ "pid": 1, "tid": 53, "ts": 168496.5057373047, "dur": 6789.400100708008, "ph": "X", "name": "HashOfAllFilesWithProviderExtensionInDirectory", "args": { "durationMS": 6.789400100708008, "detail": ".c C:\\Program Files\\Unity\\Hub\\Editor\\2020.3.6f1\\Editor\\Data\\il2cpp\\external\\bdwgc" } },
{ "pid": 1, "tid": 54, "ph": "M", "name": "thread_name", "args": { "name": "" } },
{ "pid": 1, "tid": 54, "ts": 166954.60510253906, "dur": 1938.5000467300415, "ph": "X", "name": "FileHashProvider.Initialize", "args": { "durationMS": 1.9385000467300415, "detail": "C:\\Program Files\\Unity\\Hub\\Editor\\2020.3.6f1\\Editor\\Data\\il2cpp\\libil2cpp\\codegen" } },
{ "pid": 1, "tid": 54, "ts": 166962.49389648438, "dur": 676.4000058174133, "ph": "X", "name": "HashOfAllFilesWithProviderExtensionInDirectory", "args": { "durationMS": 0.6764000058174133, "detail": ".cpp C:\\Program Files\\Unity\\Hub\\Editor\\2020.3.6f1\\Editor\\Data\\il2cpp\\libil2cpp\\codegen" } },
{ "pid": 1, "tid": 54, "ts": 167642.10510253906, "dur": 1249.6999502182007, "ph": "X", "name": "HashOfAllFilesWithProviderExtensionInDirectory", "args": { "durationMS": 1.2496999502182007, "detail": ".c C:\\Program Files\\Unity\\Hub\\Editor\\2020.3.6f1\\Editor\\Data\\il2cpp\\libil2cpp\\codegen" } },
{ "pid": 1, "tid": 54, "ts": 168894.50073242188, "dur": 1493.99995803833, "ph": "X", "name": "FileHashProvider.Initialize", "args": { "durationMS": 1.49399995803833, "detail": "C:\\Program Files\\Unity\\Hub\\Editor\\2020.3.6f1\\Editor\\Data\\il2cpp\\libil2cpp\\vm-utils" } },
{ "pid": 1, "tid": 54, "ts": 168897.49145507812, "dur": 1019.4000005722046, "ph": "X", "name": "HashOfAllFilesWithProviderExtensionInDirectory", "args": { "durationMS": 1.0194000005722046, "detail": ".cpp C:\\Program Files\\Unity\\Hub\\Editor\\2020.3.6f1\\Editor\\Data\\il2cpp\\libil2cpp\\vm-utils" } },
{ "pid": 1, "tid": 54, "ts": 169920.7000732422, "dur": 465.2999937534332, "ph": "X", "name": "HashOfAllFilesWithProviderExtensionInDirectory", "args": { "durationMS": 0.4652999937534332, "detail": ".c C:\\Program Files\\Unity\\Hub\\Editor\\2020.3.6f1\\Editor\\Data\\il2cpp\\libil2cpp\\vm-utils" } },
{ "pid": 1, "tid": 55, "ph": "M", "name": "thread_name", "args": { "name": "" } },
{ "pid": 1, "tid": 55, "ts": 167091.70532226562, "dur": 1381.2999725341797, "ph": "X", "name": "FileHashProvider.Initialize", "args": { "durationMS": 1.3812999725341797, "detail": "C:\\Program Files\\Unity\\Hub\\Editor\\2020.3.6f1\\Editor\\Data\\il2cpp\\libil2cpp\\debugger" } },
{ "pid": 1, "tid": 55, "ts": 167097.30529785156, "dur": 675.4999756813049, "ph": "X", "name": "HashOfAllFilesWithProviderExtensionInDirectory", "args": { "durationMS": 0.6754999756813049, "detail": ".cpp C:\\Program Files\\Unity\\Hub\\Editor\\2020.3.6f1\\Editor\\Data\\il2cpp\\libil2cpp\\debugger" } },
{ "pid": 1, "tid": 55, "ts": 167780.8074951172, "dur": 690.8000111579895, "ph": "X", "name": "HashOfAllFilesWithProviderExtensionInDirectory", "args": { "durationMS": 0.6908000111579895, "detail": ".c C:\\Program Files\\Unity\\Hub\\Editor\\2020.3.6f1\\Editor\\Data\\il2cpp\\libil2cpp\\debugger" } },
{ "pid": 1, "tid": 55, "ts": 168492.00439453125, "dur": 1983.5000038146973, "ph": "X", "name": "FileHashProvider.Initialize", "args": { "durationMS": 1.9835000038146973, "detail": "C:\\Program Files\\Unity\\Hub\\Editor\\2020.3.6f1\\Editor\\Data\\il2cpp\\libil2cpp\\utils" } },
{ "pid": 1, "tid": 55, "ts": 168534.89685058594, "dur": 1498.6000061035156, "ph": "X", "name": "HashOfAllFilesWithProviderExtensionInDirectory", "args": { "durationMS": 1.4986000061035156, "detail": ".cpp C:\\Program Files\\Unity\\Hub\\Editor\\2020.3.6f1\\Editor\\Data\\il2cpp\\libil2cpp\\utils" } },
{ "pid": 1, "tid": 55, "ts": 170037.3992919922, "dur": 436.39999628067017, "ph": "X", "name": "HashOfAllFilesWithProviderExtensionInDirectory", "args": { "durationMS": 0.43639999628067017, "detail": ".c C:\\Program Files\\Unity\\Hub\\Editor\\2020.3.6f1\\Editor\\Data\\il2cpp\\libil2cpp\\utils" } },
{ "pid": 1, "tid": 56, "ph": "M", "name": "thread_name", "args": { "name": "" } },
{ "pid": 1, "tid": 56, "ts": 167213.7908935547, "dur": 2696.500062942505, "ph": "X", "name": "FileHashProvider.Initialize", "args": { "durationMS": 2.696500062942505, "detail": "C:\\Program Files\\Unity\\Hub\\Editor\\2020.3.6f1\\Editor\\Data\\il2cpp\\libil2cpp\\gc" } },
{ "pid": 1, "tid": 56, "ts": 167218.7957763672, "dur": 1209.3000411987305, "ph": "X", "name": "HashOfAllFilesWithProviderExtensionInDirectory", "args": { "durationMS": 1.2093000411987305, "detail": ".cpp C:\\Program Files\\Unity\\Hub\\Editor\\2020.3.6f1\\Editor\\Data\\il2cpp\\libil2cpp\\gc" } },
{ "pid": 1, "tid": 56, "ts": 168431.396484375, "dur": 1477.6999950408936, "ph": "X", "name": "HashOfAllFilesWithProviderExtensionInDirectory", "args": { "durationMS": 1.4776999950408936, "detail": ".c C:\\Program Files\\Unity\\Hub\\Editor\\2020.3.6f1\\Editor\\Data\\il2cpp\\libil2cpp\\gc" } },
{ "pid": 1, "tid": 57, "ph": "M", "name": "thread_name", "args": { "name": "" } },
{ "pid": 1, "tid": 57, "ts": 167317.5048828125, "dur": 11323.100090026855, "ph": "X", "name": "FileHashProvider.Initialize", "args": { "durationMS": 11.323100090026855, "detail": "C:\\Program Files\\Unity\\Hub\\Editor\\2020.3.6f1\\Editor\\Data\\il2cpp\\libil2cpp\\icalls" } },
{ "pid": 1, "tid": 57, "ts": 167321.59423828125, "dur": 9412.099838256836, "ph": "X", "name": "HashOfAllFilesWithProviderExtensionInDirectory", "args": { "durationMS": 9.412099838256836, "detail": ".cpp C:\\Program Files\\Unity\\Hub\\Editor\\2020.3.6f1\\Editor\\Data\\il2cpp\\libil2cpp\\icalls" } },
{ "pid": 1, "tid": 57, "ts": 176740.7989501953, "dur": 1883.2999467849731, "ph": "X", "name": "HashOfAllFilesWithProviderExtensionInDirectory", "args": { "durationMS": 1.8832999467849731, "detail": ".c C:\\Program Files\\Unity\\Hub\\Editor\\2020.3.6f1\\Editor\\Data\\il2cpp\\libil2cpp\\icalls" } },
{ "pid": 1, "tid": 58, "ph": "M", "name": "thread_name", "args": { "name": "" } },
{ "pid": 1, "tid": 58, "ts": 167578.79638671875, "dur": 2492.500066757202, "ph": "X", "name": "FileHashProvider.Initialize", "args": { "durationMS": 2.492500066757202, "detail": "C:\\Program Files\\Unity\\Hub\\Editor\\2020.3.6f1\\Editor\\Data\\il2cpp\\libil2cpp\\metadata" } },
{ "pid": 1, "tid": 58, "ts": 167585.38818359375, "dur": 1418.4000492095947, "ph": "X", "name": "HashOfAllFilesWithProviderExtensionInDirectory", "args": { "durationMS": 1.4184000492095947, "detail": ".cpp C:\\Program Files\\Unity\\Hub\\Editor\\2020.3.6f1\\Editor\\Data\\il2cpp\\libil2cpp\\metadata" } },
{ "pid": 1, "tid": 58, "ts": 169014.09912109375, "dur": 1055.0999641418457, "ph": "X", "name": "HashOfAllFilesWithProviderExtensionInDirectory", "args": { "durationMS": 1.0550999641418457, "detail": ".c C:\\Program Files\\Unity\\Hub\\Editor\\2020.3.6f1\\Editor\\Data\\il2cpp\\libil2cpp\\metadata" } },
{ "pid": 1, "tid": 59, "ph": "M", "name": "thread_name", "args": { "name": "" } },
{ "pid": 1, "tid": 59, "ts": 167706.20727539062, "dur": 2204.400062561035, "ph": "X", "name": "FileHashProvider.Initialize", "args": { "durationMS": 2.204400062561035, "detail": "C:\\Program Files\\Unity\\Hub\\Editor\\2020.3.6f1\\Editor\\Data\\il2cpp\\libil2cpp\\mono" } },
{ "pid": 1, "tid": 59, "ts": 167710.8917236328, "dur": 1157.2999954223633, "ph": "X", "name": "HashOfAllFilesWithProviderExtensionInDirectory", "args": { "durationMS": 1.1572999954223633, "detail": ".cpp C:\\Program Files\\Unity\\Hub\\Editor\\2020.3.6f1\\Editor\\Data\\il2cpp\\libil2cpp\\mono" } },
{ "pid": 1, "tid": 59, "ts": 168871.39892578125, "dur": 1037.500023841858, "ph": "X", "name": "HashOfAllFilesWithProviderExtensionInDirectory", "args": { "durationMS": 1.037500023841858, "detail": ".c C:\\Program Files\\Unity\\Hub\\Editor\\2020.3.6f1\\Editor\\Data\\il2cpp\\libil2cpp\\mono" } },
{ "pid": 1, "tid": 60, "ph": "M", "name": "thread_name", "args": { "name": "" } },
{ "pid": 1, "tid": 60, "ts": 168339.3096923828, "dur": 10767.7001953125, "ph": "X", "name": "FileHashProvider.Initialize", "args": { "durationMS": 10.7677001953125, "detail": "C:\\Program Files\\Unity\\Hub\\Editor\\2020.3.6f1\\Editor\\Data\\il2cpp\\libil2cpp\\os" } },
{ "pid": 1, "tid": 60, "ts": 168345.9930419922, "dur": 10099.499702453613, "ph": "X", "name": "HashOfAllFilesWithProviderExtensionInDirectory", "args": { "durationMS": 10.099499702453613, "detail": ".cpp C:\\Program Files\\Unity\\Hub\\Editor\\2020.3.6f1\\Editor\\Data\\il2cpp\\libil2cpp\\os" } },
{ "pid": 1, "tid": 60, "ts": 178448.8983154297, "dur": 644.9000239372253, "ph": "X", "name": "HashOfAllFilesWithProviderExtensionInDirectory", "args": { "durationMS": 0.6449000239372253, "detail": ".c C:\\Program Files\\Unity\\Hub\\Editor\\2020.3.6f1\\Editor\\Data\\il2cpp\\libil2cpp\\os" } },
{ "pid": 1, "tid": 61, "ph": "M", "name": "thread_name", "args": { "name": "" } },
{ "pid": 1, "tid": 61, "ts": 168882.4920654297, "dur": 3846.8000888824463, "ph": "X", "name": "FileHashProvider.Initialize", "args": { "durationMS": 3.8468000888824463, "detail": "C:\\Program Files\\Unity\\Hub\\Editor\\2020.3.6f1\\Editor\\Data\\il2cpp\\libil2cpp\\vm" } },
{ "pid": 1, "tid": 61, "ts": 168895.7061767578, "dur": 3473.299980163574, "ph": "X", "name": "HashOfAllFilesWithProviderExtensionInDirectory", "args": { "durationMS": 3.473299980163574, "detail": ".cpp C:\\Program Files\\Unity\\Hub\\Editor\\2020.3.6f1\\Editor\\Data\\il2cpp\\libil2cpp\\vm" } },
{ "pid": 1, "tid": 61, "ts": 172372.90954589844, "dur": 349.7999906539917, "ph": "X", "name": "HashOfAllFilesWithProviderExtensionInDirectory", "args": { "durationMS": 0.3497999906539917, "detail": ".c C:\\Program Files\\Unity\\Hub\\Editor\\2020.3.6f1\\Editor\\Data\\il2cpp\\libil2cpp\\vm" } },
{ "pid": 1, "tid": 97, "ph": "M", "name": "thread_name", "args": { "name": "" } },
{ "pid": 1, "tid": 97, "ts": 173025.20751953125, "dur": 495.2000081539154, "ph": "X", "name": "HashOfFile", "args": { "durationMS": 0.4952000081539154, "detail": "C:\\Program Files\\Unity\\Hub\\Editor\\2020.3.6f1\\Editor\\Data\\il2cpp\\external\\bdwgc\\os_dep.c" } },
{ "pid": 1, "tid": 97, "ts": 174758.30078125, "dur": 445.3999996185303, "ph": "X", "name": "HashOfFile", "args": { "durationMS": 0.4453999996185303, "detail": "C:\\Program Files\\Unity\\Hub\\Editor\\2020.3.6f1\\Editor\\Data\\il2cpp\\external\\bdwgc\\win32_threads.c" } },
{ "pid": 1, "tid": 100, "ph": "M", "name": "thread_name", "args": { "name": "" } },
{ "pid": 1, "tid": 100, "ts": 172926.1932373047, "dur": 347.09998965263367, "ph": "X", "name": "HashOfFile", "args": { "durationMS": 0.34709998965263367, "detail": "C:\\Program Files\\Unity\\Hub\\Editor\\2020.3.6f1\\Editor\\Data\\il2cpp\\libil2cpp\\os\\Messages.cpp" } },
{ "pid": 1, "tid": 109, "ph": "M", "name": "thread_name", "args": { "name": "" } },
{ "pid": 1, "tid": 109, "ts": 190833.80126953125, "dur": 30753.400802612305, "ph": "X", "name": "HashCompilerInvocation", "args": { "durationMS": 30.753400802612305, "detail": "Il2CppCCalculateFieldValues.cpp" } },
{ "pid": 1, "tid": 109, "ts": 221611.4959716797, "dur": 8969.200134277344, "ph": "X", "name": "HashCompilerInvocation", "args": { "durationMS": 8.969200134277344, "detail": "mscorlib15.cpp" } },
{ "pid": 1, "tid": 109, "ts": 230606.4910888672, "dur": 11435.999870300293, "ph": "X", "name": "HashCompilerInvocation", "args": { "durationMS": 11.435999870300293, "detail": "Il2CppGenericMethodPointerTable.cpp" } },
{ "pid": 1, "tid": 109, "ts": 242067.0928955078, "dur": 19856.10008239746, "ph": "X", "name": "HashCompilerInvocation", "args": { "durationMS": 19.85610008239746, "detail": "mscorlib_Attr.cpp" } },
{ "pid": 1, "tid": 109, "ts": 261945.00732421875, "dur": 1303.5999536514282, "ph": "X", "name": "HashCompilerInvocation", "args": { "durationMS": 1.3035999536514282, "detail": "UnityEngine.SpriteShapeModule_Attr.cpp" } },
{ "pid": 1, "tid": 109, "ts": 263268.98193359375, "dur": 1606.0999631881714, "ph": "X", "name": "HashCompilerInvocation", "args": { "durationMS": 1.6060999631881714, "detail": "Assembly-CSharp_Attr.cpp" } },
{ "pid": 1, "tid": 109, "ts": 264897.7966308594, "dur": 7335.100173950195, "ph": "X", "name": "HashCompilerInvocation", "args": { "durationMS": 7.335100173950195, "detail": "System.Core.cpp" } },
{ "pid": 1, "tid": 109, "ts": 272325.8056640625, "dur": 1392.4000263214111, "ph": "X", "name": "HashCompilerInvocation", "args": { "durationMS": 1.3924000263214111, "detail": "crc32.c" } },
{ "pid": 1, "tid": 109, "ts": 273749.2980957031, "dur": 2149.8000621795654, "ph": "X", "name": "HashCompilerInvocation", "args": { "durationMS": 2.1498000621795654, "detail": "UnityEngine.TilemapModule.cpp" } },
{ "pid": 1, "tid": 109, "ts": 275920.59326171875, "dur": 2682.499885559082, "ph": "X", "name": "HashCompilerInvocation", "args": { "durationMS": 2.682499885559082, "detail": "Il2CppReversePInvokeWrapperTable.cpp" } },
{ "pid": 1, "tid": 109, "ts": 278627.2888183594, "dur": 2707.70001411438, "ph": "X", "name": "HashCompilerInvocation", "args": { "durationMS": 2.70770001411438, "detail": "UnityEngine.cpp" } },
{ "pid": 1, "tid": 109, "ts": 281365.3869628906, "dur": 8093.600273132324, "ph": "X", "name": "HashCompilerInvocation", "args": { "durationMS": 8.093600273132324, "detail": "UnityEngine.GridModule_CodeGen.c" } },
{ "pid": 1, "tid": 109, "ts": 289485.3210449219, "dur": 1989.300012588501, "ph": "X", "name": "HashCompilerInvocation", "args": { "durationMS": 1.989300012588501, "detail": "Il2CppGenericComDefinitions16.cpp" } },
{ "pid": 1, "tid": 109, "ts": 291505.0048828125, "dur": 1936.5999698638916, "ph": "X", "name": "HashCompilerInvocation", "args": { "durationMS": 1.9365999698638916, "detail": "Il2CppGenericComDefinitions23.cpp" } },
{ "pid": 1, "tid": 112, "ph": "M", "name": "thread_name", "args": { "name": "" } },
{ "pid": 1, "tid": 112, "ts": 190839.50805664062, "dur": 21655.399322509766, "ph": "X", "name": "HashCompilerInvocation", "args": { "durationMS": 21.655399322509766, "detail": "GenericMethods2.cpp" } },
{ "pid": 1, "tid": 112, "ts": 212520.49255371094, "dur": 7820.099830627441, "ph": "X", "name": "HashCompilerInvocation", "args": { "durationMS": 7.820099830627441, "detail": "mscorlib.cpp" } },
{ "pid": 1, "tid": 112, "ts": 220367.49267578125, "dur": 10564.599990844727, "ph": "X", "name": "HashCompilerInvocation", "args": { "durationMS": 10.564599990844727, "detail": "mscorlib6.cpp" } },
{ "pid": 1, "tid": 112, "ts": 230959.7930908203, "dur": 7593.900203704834, "ph": "X", "name": "HashCompilerInvocation", "args": { "durationMS": 7.593900203704834, "detail": "Generics1.cpp" } },
{ "pid": 1, "tid": 112, "ts": 238578.79638671875, "dur": 4995.60022354126, "ph": "X", "name": "HashCompilerInvocation", "args": { "durationMS": 4.99560022354126, "detail": "System.cpp" } },
{ "pid": 1, "tid": 112, "ts": 243599.8992919922, "dur": 18884.700775146484, "ph": "X", "name": "HashCompilerInvocation", "args": { "durationMS": 18.884700775146484, "detail": "UnityEngine.IMGUIModule.cpp" } },
{ "pid": 1, "tid": 112, "ts": 262508.7890625, "dur": 1309.1000318527222, "ph": "X", "name": "HashCompilerInvocation", "args": { "durationMS": 1.3091000318527222, "detail": "inflate.c" } },
{ "pid": 1, "tid": 112, "ts": 263840.7897949219, "dur": 1564.5999908447266, "ph": "X", "name": "HashCompilerInvocation", "args": { "durationMS": 1.5645999908447266, "detail": "il2cpp-api.cpp" } },
{ "pid": 1, "tid": 112, "ts": 265433.28857421875, "dur": 7603.000164031982, "ph": "X", "name": "HashCompilerInvocation", "args": { "durationMS": 7.603000164031982, "detail": "gzread.c" } },
{ "pid": 1, "tid": 112, "ts": 273063.0798339844, "dur": 2349.2000102996826, "ph": "X", "name": "HashCompilerInvocation", "args": { "durationMS": 2.3492000102996826, "detail": "inffast.c" } },
{ "pid": 1, "tid": 112, "ts": 275436.70654296875, "dur": 6903.299808502197, "ph": "X", "name": "HashCompilerInvocation", "args": { "durationMS": 6.903299808502197, "detail": "gc.c" } },
{ "pid": 1, "tid": 112, "ts": 282364.990234375, "dur": 9077.699661254883, "ph": "X", "name": "HashCompilerInvocation", "args": { "durationMS": 9.077699661254883, "detail": "Il2CppGenericComDefinitions13.cpp" } },
{ "pid": 1, "tid": 112, "ts": 291469.1162109375, "dur": 1727.3000478744507, "ph": "X", "name": "HashCompilerInvocation", "args": { "durationMS": 1.7273000478744507, "detail": "Il2CppGenericComDefinitions22.cpp" } },
{ "pid": 1, "tid": 111, "ph": "M", "name": "thread_name", "args": { "name": "" } },
{ "pid": 1, "tid": 111, "ts": 190842.6971435547, "dur": 23340.200424194336, "ph": "X", "name": "HashCompilerInvocation", "args": { "durationMS": 23.340200424194336, "detail": "Unity.TextMeshPro2.cpp" } },
{ "pid": 1, "tid": 111, "ts": 214211.80725097656, "dur": 12032.899856567383, "ph": "X", "name": "HashCompilerInvocation", "args": { "durationMS": 12.032899856567383, "detail": "Unity.TextMeshPro1.cpp" } },
{ "pid": 1, "tid": 111, "ts": 226270.99609375, "dur": 12491.999626159668, "ph": "X", "name": "HashCompilerInvocation", "args": { "durationMS": 12.491999626159668, "detail": "UnityEngine.UI2.cpp" } },
{ "pid": 1, "tid": 111, "ts": 238787.8875732422, "dur": 4563.899993896484, "ph": "X", "name": "HashCompilerInvocation", "args": { "durationMS": 4.563899993896484, "detail": "Generics6.cpp" } },
{ "pid": 1, "tid": 111, "ts": 243376.40380859375, "dur": 18829.1015625, "ph": "X", "name": "HashCompilerInvocation", "args": { "durationMS": 18.8291015625, "detail": "UnityEngine.AndroidJNIModule.cpp" } },
{ "pid": 1, "tid": 111, "ts": 262230.5908203125, "dur": 1702.1000385284424, "ph": "X", "name": "HashCompilerInvocation", "args": { "durationMS": 1.7021000385284424, "detail": "deflate.c" } },
{ "pid": 1, "tid": 111, "ts": 263955.50537109375, "dur": 1536.3999605178833, "ph": "X", "name": "HashCompilerInvocation", "args": { "durationMS": 1.5363999605178833, "detail": "UnityEngine.PhysicsModule.cpp" } },
{ "pid": 1, "tid": 111, "ts": 265512.9089355469, "dur": 9445.799827575684, "ph": "X", "name": "HashCompilerInvocation", "args": { "durationMS": 9.445799827575684, "detail": "Lump_libil2cpp_icalls.cpp" } },
{ "pid": 1, "tid": 111, "ts": 274985.6872558594, "dur": 2413.100004196167, "ph": "X", "name": "HashCompilerInvocation", "args": { "durationMS": 2.413100004196167, "detail": "adler32.c" } },
{ "pid": 1, "tid": 111, "ts": 277425.9948730469, "dur": 4156.899929046631, "ph": "X", "name": "HashCompilerInvocation", "args": { "durationMS": 4.156899929046631, "detail": "Lump_libil2cpp_metadata.cpp" } },
{ "pid": 1, "tid": 111, "ts": 281608.70361328125, "dur": 8657.19985961914, "ph": "X", "name": "HashCompilerInvocation", "args": { "durationMS": 8.65719985961914, "detail": "UnityEngine_CodeGen.c" } },
{ "pid": 1, "tid": 111, "ts": 290287.6892089844, "dur": 1462.499976158142, "ph": "X", "name": "HashCompilerInvocation", "args": { "durationMS": 1.462499976158142, "detail": "Il2CppGenericComDefinitions19.cpp" } },
{ "pid": 1, "tid": 111, "ts": 291776.3977050781, "dur": 1854.200005531311, "ph": "X", "name": "HashCompilerInvocation", "args": { "durationMS": 1.854200005531311, "detail": "Il2CppGenericComDefinitions7.cpp" } },
{ "pid": 1, "tid": 117, "ph": "M", "name": "thread_name", "args": { "name": "" } },
{ "pid": 1, "tid": 117, "ts": 190843.3074951172, "dur": 20972.898483276367, "ph": "X", "name": "HashCompilerInvocation", "args": { "durationMS": 20.972898483276367, "detail": "Generics2.cpp" } },
{ "pid": 1, "tid": 117, "ts": 212315.70434570312, "dur": 8492.69962310791, "ph": "X", "name": "HashCompilerInvocation", "args": { "durationMS": 8.49269962310791, "detail": "mscorlib10.cpp" } },
{ "pid": 1, "tid": 117, "ts": 220836.41052246094, "dur": 11034.99984741211, "ph": "X", "name": "HashCompilerInvocation", "args": { "durationMS": 11.03499984741211, "detail": "mscorlib7.cpp" } },
{ "pid": 1, "tid": 117, "ts": 231898.28491210938, "dur": 9471.400260925293, "ph": "X", "name": "HashCompilerInvocation", "args": { "durationMS": 9.471400260925293, "detail": "UnityEngine.CoreModule1.cpp" } },
{ "pid": 1, "tid": 117, "ts": 241396.6064453125, "dur": 11684.399604797363, "ph": "X", "name": "HashCompilerInvocation", "args": { "durationMS": 11.684399604797363, "detail": "UnityEngine.CoreModule_Attr.cpp" } },
{ "pid": 1, "tid": 117, "ts": 253123.79455566406, "dur": 1681.1000108718872, "ph": "X", "name": "HashCompilerInvocation", "args": { "durationMS": 1.6811000108718872, "detail": "UnityEngine.TextCoreModule.cpp" } },
{ "pid": 1, "tid": 117, "ts": 254846.58813476562, "dur": 1607.200026512146, "ph": "X", "name": "HashCompilerInvocation", "args": { "durationMS": 1.607200026512146, "detail": "Il2CppGenericMethodTable.c" } },
{ "pid": 1, "tid": 117, "ts": 256481.50634765625, "dur": 1544.700026512146, "ph": "X", "name": "HashCompilerInvocation", "args": { "durationMS": 1.544700026512146, "detail": "UnityEngine.SharedInternalsModule.cpp" } },
{ "pid": 1, "tid": 117, "ts": 258048.52294921875, "dur": 1536.9999408721924, "ph": "X", "name": "HashCompilerInvocation", "args": { "durationMS": 1.5369999408721924, "detail": "UnityEngine.AudioModule_Attr.cpp" } },
{ "pid": 1, "tid": 117, "ts": 259618.62182617188, "dur": 3351.5000343322754, "ph": "X", "name": "HashCompilerInvocation", "args": { "durationMS": 3.3515000343322754, "detail": "UnityEngine.Physics2DModule_Attr.cpp" } },
{ "pid": 1, "tid": 117, "ts": 262993.896484375, "dur": 1737.3000383377075, "ph": "X", "name": "HashCompilerInvocation", "args": { "durationMS": 1.7373000383377075, "detail": "Unity.2D.IK.Runtime_Attr.cpp" } },
{ "pid": 1, "tid": 117, "ts": 264765.1062011719, "dur": 7580.100059509277, "ph": "X", "name": "HashCompilerInvocation", "args": { "durationMS": 7.580100059509277, "detail": "infback.c" } },
{ "pid": 1, "tid": 117, "ts": 272366.1193847656, "dur": 1284.10005569458, "ph": "X", "name": "HashCompilerInvocation", "args": { "durationMS": 1.28410005569458, "detail": "UnityEngine.AudioModule_CodeGen.c" } },
{ "pid": 1, "tid": 117, "ts": 273673.27880859375, "dur": 2199.700117111206, "ph": "X", "name": "HashCompilerInvocation", "args": { "durationMS": 2.199700117111206, "detail": "zutil.c" } },
{ "pid": 1, "tid": 117, "ts": 275895.2941894531, "dur": 2753.2999515533447, "ph": "X", "name": "HashCompilerInvocation", "args": { "durationMS": 2.7532999515533447, "detail": "UnityEngine.PhysicsModule_CodeGen.c" } },
{ "pid": 1, "tid": 117, "ts": 278671.4782714844, "dur": 3306.299924850464, "ph": "X", "name": "HashCompilerInvocation", "args": { "durationMS": 3.306299924850464, "detail": "Lump_libil2cpp_mono.cpp" } },
{ "pid": 1, "tid": 117, "ts": 282001.89208984375, "dur": 7343.400001525879, "ph": "X", "name": "HashCompilerInvocation", "args": { "durationMS": 7.343400001525879, "detail": "Il2CppGenericComDefinitions.cpp" } },
{ "pid": 1, "tid": 117, "ts": 289689.02587890625, "dur": 1875.3999471664429, "ph": "X", "name": "HashCompilerInvocation", "args": { "durationMS": 1.8753999471664429, "detail": "Il2CppGenericComDefinitions17.cpp" } },
{ "pid": 1, "tid": 117, "ts": 291587.7990722656, "dur": 1545.4000234603882, "ph": "X", "name": "HashCompilerInvocation", "args": { "durationMS": 1.5454000234603882, "detail": "Il2CppGenericComDefinitions3.cpp" } },
{ "pid": 1, "tid": 118, "ph": "M", "name": "thread_name", "args": { "name": "" } },
{ "pid": 1, "tid": 118, "ts": 190847.7020263672, "dur": 20871.79946899414, "ph": "X", "name": "HashCompilerInvocation", "args": { "durationMS": 20.87179946899414, "detail": "mscorlib_CodeGen.c" } },
{ "pid": 1, "tid": 118, "ts": 212807.60192871094, "dur": 9528.300285339355, "ph": "X", "name": "HashCompilerInvocation", "args": { "durationMS": 9.528300285339355, "detail": "Il2CppTypeDefinitions.c" } },
{ "pid": 1, "tid": 118, "ts": 222360.01586914062, "dur": 8193.300247192383, "ph": "X", "name": "HashCompilerInvocation", "args": { "durationMS": 8.193300247192383, "detail": "Unity.TextMeshPro4.cpp" } },
{ "pid": 1, "tid": 118, "ts": 230579.89501953125, "dur": 7695.700168609619, "ph": "X", "name": "HashCompilerInvocation", "args": { "durationMS": 7.695700168609619, "detail": "Generics7.cpp" } },
{ "pid": 1, "tid": 118, "ts": 238323.6083984375, "dur": 6478.300094604492, "ph": "X", "name": "HashCompilerInvocation", "args": { "durationMS": 6.478300094604492, "detail": "UnityEngine.UI1.cpp" } },
{ "pid": 1, "tid": 118, "ts": 250113.78479003906, "dur": 2510.6000900268555, "ph": "X", "name": "HashCompilerInvocation", "args": { "durationMS": 2.5106000900268555, "detail": "Il2CppGenericInstDefinitions.c" } },
{ "pid": 1, "tid": 118, "ts": 252654.99877929688, "dur": 1924.299955368042, "ph": "X", "name": "HashCompilerInvocation", "args": { "durationMS": 1.924299955368042, "detail": "GenericMethods3.cpp" } },
{ "pid": 1, "tid": 118, "ts": 254605.89599609375, "dur": 1748.7000226974487, "ph": "X", "name": "HashCompilerInvocation", "args": { "durationMS": 1.7487000226974487, "detail": "Il2CppCCTypeValuesTable.cpp" } },
{ "pid": 1, "tid": 118, "ts": 256378.38745117188, "dur": 1394.1999673843384, "ph": "X", "name": "HashCompilerInvocation", "args": { "durationMS": 1.3941999673843384, "detail": "Il2CppGenericClassTable.c" } },
{ "pid": 1, "tid": 118, "ts": 257796.5087890625, "dur": 2068.7999725341797, "ph": "X", "name": "HashCompilerInvocation", "args": { "durationMS": 2.0687999725341797, "detail": "Mono.Security.cpp" } },
{ "pid": 1, "tid": 118, "ts": 259889.61791992188, "dur": 3055.3998947143555, "ph": "X", "name": "HashCompilerInvocation", "args": { "durationMS": 3.0553998947143555, "detail": "UnityEngine.AndroidJNIModule_CodeGen.c" } },
{ "pid": 1, "tid": 118, "ts": 262968.3837890625, "dur": 1488.1000518798828, "ph": "X", "name": "HashCompilerInvocation", "args": { "durationMS": 1.4881000518798828, "detail": "System.Xml_Attr.cpp" } },
{ "pid": 1, "tid": 118, "ts": 264479.2175292969, "dur": 7654.200077056885, "ph": "X", "name": "HashCompilerInvocation", "args": { "durationMS": 7.654200077056885, "detail": "Assembly-CSharp_CodeGen.c" } },
{ "pid": 1, "tid": 118, "ts": 272159.7900390625, "dur": 1542.4000024795532, "ph": "X", "name": "HashCompilerInvocation", "args": { "durationMS": 1.5424000024795532, "detail": "UnityEngine.TextRenderingModule_CodeGen.c" } },
{ "pid": 1, "tid": 118, "ts": 273732.60498046875, "dur": 1597.2000360488892, "ph": "X", "name": "HashCompilerInvocation", "args": { "durationMS": 1.5972000360488892, "detail": "System.Configuration_CodeGen.c" } },
{ "pid": 1, "tid": 118, "ts": 275351.8981933594, "dur": 2143.1000232696533, "ph": "X", "name": "HashCompilerInvocation", "args": { "durationMS": 2.1431000232696533, "detail": "UnityEngine.GridModule.cpp" } },
{ "pid": 1, "tid": 118, "ts": 277539.2150878906, "dur": 3396.8000411987305, "ph": "X", "name": "HashCompilerInvocation", "args": { "durationMS": 3.3968000411987305, "detail": "Lump_libil2cpp_utils.cpp" } },
{ "pid": 1, "tid": 118, "ts": 280959.5031738281, "dur": 5696.199893951416, "ph": "X", "name": "HashCompilerInvocation", "args": { "durationMS": 5.696199893951416, "detail": "UnityEngine.TilemapModule_CodeGen.c" } },
{ "pid": 1, "tid": 118, "ts": 286681.396484375, "dur": 4996.9000816345215, "ph": "X", "name": "HashCompilerInvocation", "args": { "durationMS": 4.9969000816345215, "detail": "Il2CppGenericComDefinitions14.cpp" } },
{ "pid": 1, "tid": 118, "ts": 291700.7141113281, "dur": 2258.699893951416, "ph": "X", "name": "HashCompilerInvocation", "args": { "durationMS": 2.258699893951416, "detail": "Il2CppGenericComDefinitions5.cpp" } },
{ "pid": 1, "tid": 113, "ph": "M", "name": "thread_name", "args": { "name": "" } },
{ "pid": 1, "tid": 113, "ts": 190849.8077392578, "dur": 21233.400344848633, "ph": "X", "name": "HashCompilerInvocation", "args": { "durationMS": 21.233400344848633, "detail": "Il2CppInvokerTable.cpp" } },
{ "pid": 1, "tid": 113, "ts": 212313.8885498047, "dur": 10337.599754333496, "ph": "X", "name": "HashCompilerInvocation", "args": { "durationMS": 10.337599754333496, "detail": "mscorlib1.cpp" } },
{ "pid": 1, "tid": 113, "ts": 222676.78833007812, "dur": 7117.700099945068, "ph": "X", "name": "HashCompilerInvocation", "args": { "durationMS": 7.117700099945068, "detail": "mscorlib14.cpp" } },
{ "pid": 1, "tid": 113, "ts": 229822.49450683594, "dur": 8506.400108337402, "ph": "X", "name": "HashCompilerInvocation", "args": { "durationMS": 8.506400108337402, "detail": "System1.cpp" } },
{ "pid": 1, "tid": 113, "ts": 238355.712890625, "dur": 6104.899883270264, "ph": "X", "name": "HashCompilerInvocation", "args": { "durationMS": 6.104899883270264, "detail": "Il2CppMetadataUsage.c" } },
{ "pid": 1, "tid": 113, "ts": 244488.6016845703, "dur": 7610.7001304626465, "ph": "X", "name": "HashCompilerInvocation", "args": { "durationMS": 7.6107001304626465, "detail": "UnityEngine.UI_CodeGen.c" } },
{ "pid": 1, "tid": 113, "ts": 252127.4871826172, "dur": 2127.300024032593, "ph": "X", "name": "HashCompilerInvocation", "args": { "durationMS": 2.1273000240325928, "detail": "char-conversions.cpp" } },
{ "pid": 1, "tid": 113, "ts": 254278.91540527344, "dur": 1588.2999897003174, "ph": "X", "name": "HashCompilerInvocation", "args": { "durationMS": 1.5882999897003174, "detail": "Unity.TextMeshPro_Attr.cpp" } },
{ "pid": 1, "tid": 113, "ts": 255883.69750976562, "dur": 1228.9999723434448, "ph": "X", "name": "HashCompilerInvocation", "args": { "durationMS": 1.2289999723434448, "detail": "UnityEngine.IMGUIModule_Attr.cpp" } },
{ "pid": 1, "tid": 113, "ts": 257140.41137695312, "dur": 1268.2000398635864, "ph": "X", "name": "HashCompilerInvocation", "args": { "durationMS": 1.2682000398635864, "detail": "Il2CppInteropDataTable.cpp" } },
{ "pid": 1, "tid": 113, "ts": 258433.77685546875, "dur": 2276.7999172210693, "ph": "X", "name": "HashCompilerInvocation", "args": { "durationMS": 2.2767999172210693, "detail": "Il2CppCCFieldValuesTable.cpp" } },
{ "pid": 1, "tid": 113, "ts": 260738.18969726562, "dur": 2374.9001026153564, "ph": "X", "name": "HashCompilerInvocation", "args": { "durationMS": 2.3749001026153564, "detail": "UnityEngine.InputLegacyModule_Attr.cpp" } },
{ "pid": 1, "tid": 113, "ts": 263138.2141113281, "dur": 1518.0000066757202, "ph": "X", "name": "HashCompilerInvocation", "args": { "durationMS": 1.5180000066757202, "detail": "System.Configuration.cpp" } },
{ "pid": 1, "tid": 113, "ts": 264694.3054199219, "dur": 10404.399871826172, "ph": "X", "name": "HashCompilerInvocation", "args": { "durationMS": 10.404399871826172, "detail": "UnityEngine.AnimationModule_CodeGen.c" } },
{ "pid": 1, "tid": 113, "ts": 275129.9133300781, "dur": 2861.999988555908, "ph": "X", "name": "HashCompilerInvocation", "args": { "durationMS": 2.861999988555908, "detail": "Il2CppCodeRegistration.cpp" } },
{ "pid": 1, "tid": 113, "ts": 278017.88330078125, "dur": 3808.3999156951904, "ph": "X", "name": "HashCompilerInvocation", "args": { "durationMS": 3.8083999156951904, "detail": "Lump_libil2cpp_vm-utils.cpp" } },
{ "pid": 1, "tid": 113, "ts": 281851.5930175781, "dur": 9504.199981689453, "ph": "X", "name": "HashCompilerInvocation", "args": { "durationMS": 9.504199981689453, "detail": "Lump_libil2cpp_codegen.cpp" } },
{ "pid": 1, "tid": 113, "ts": 291390.80810546875, "dur": 1527.1999835968018, "ph": "X", "name": "HashCompilerInvocation", "args": { "durationMS": 1.5271999835968018, "detail": "Il2CppGenericComDefinitions21.cpp" } },
{ "pid": 1, "tid": 113, "ts": 292945.00732421875, "dur": 1266.2999629974365, "ph": "X", "name": "HashCompilerInvocation", "args": { "durationMS": 1.2662999629974365, "detail": "Lump_libil2cpp_debugger.cpp" } },
{ "pid": 1, "tid": 116, "ph": "M", "name": "thread_name", "args": { "name": "" } },
{ "pid": 1, "tid": 116, "ts": 190852.79846191406, "dur": 28340.00015258789, "ph": "X", "name": "HashCompilerInvocation", "args": { "durationMS": 28.34000015258789, "detail": "Unity.TextMeshPro3.cpp" } },
{ "pid": 1, "tid": 116, "ts": 219224.09057617188, "dur": 11609.800338745117, "ph": "X", "name": "HashCompilerInvocation", "args": { "durationMS": 11.609800338745117, "detail": "mscorlib4.cpp" } },
{ "pid": 1, "tid": 116, "ts": 230859.4970703125, "dur": 7462.900161743164, "ph": "X", "name": "HashCompilerInvocation", "args": { "durationMS": 7.462900161743164, "detail": "mscorlib16.cpp" } },
{ "pid": 1, "tid": 116, "ts": 238350.11291503906, "dur": 5972.400188446045, "ph": "X", "name": "HashCompilerInvocation", "args": { "durationMS": 5.972400188446045, "detail": "UnityEngine.UI3.cpp" } },
{ "pid": 1, "tid": 116, "ts": 244348.28186035156, "dur": 17142.200469970703, "ph": "X", "name": "HashCompilerInvocation", "args": { "durationMS": 17.142200469970703, "detail": "System2.cpp" } },
{ "pid": 1, "tid": 116, "ts": 261514.80102539062, "dur": 1643.5999870300293, "ph": "X", "name": "HashCompilerInvocation", "args": { "durationMS": 1.6435999870300293, "detail": "UnityEngine.TilemapModule_Attr.cpp" } },
{ "pid": 1, "tid": 116, "ts": 263181.4880371094, "dur": 1421.9000339508057, "ph": "X", "name": "HashCompilerInvocation", "args": { "durationMS": 1.4219000339508057, "detail": "trees.c" } },
{ "pid": 1, "tid": 116, "ts": 264643.8903808594, "dur": 7489.799976348877, "ph": "X", "name": "HashCompilerInvocation", "args": { "durationMS": 7.489799976348877, "detail": "UnityEngine.UnityWebRequestModule_CodeGen.c" } },
{ "pid": 1, "tid": 116, "ts": 272162.29248046875, "dur": 1457.9999446868896, "ph": "X", "name": "HashCompilerInvocation", "args": { "durationMS": 1.4579999446868896, "detail": "gzlib.c" } },
{ "pid": 1, "tid": 116, "ts": 273643.2189941406, "dur": 2123.1000423431396, "ph": "X", "name": "HashCompilerInvocation", "args": { "durationMS": 2.1231000423431396, "detail": "UnityEngine_Attr.cpp" } },
{ "pid": 1, "tid": 116, "ts": 275788.9099121094, "dur": 4445.199966430664, "ph": "X", "name": "HashCompilerInvocation", "args": { "durationMS": 4.445199966430664, "detail": "compress.c" } },
{ "pid": 1, "tid": 116, "ts": 280261.71875, "dur": 2032.2000980377197, "ph": "X", "name": "HashCompilerInvocation", "args": { "durationMS": 2.0322000980377197, "detail": "gzclose.c" } },
{ "pid": 1, "tid": 116, "ts": 282318.115234375, "dur": 9296.299934387207, "ph": "X", "name": "HashCompilerInvocation", "args": { "durationMS": 9.296299934387207, "detail": "Il2CppGenericComDefinitions11.cpp" } },
{ "pid": 1, "tid": 116, "ts": 291634.09423828125, "dur": 1644.700050354004, "ph": "X", "name": "HashCompilerInvocation", "args": { "durationMS": 1.644700050354004, "detail": "Il2CppGenericComDefinitions4.cpp" } },
{ "pid": 1, "tid": 115, "ph": "M", "name": "thread_name", "args": { "name": "" } },
{ "pid": 1, "tid": 115, "ts": 190858.09326171875, "dur": 21092.80014038086, "ph": "X", "name": "HashCompilerInvocation", "args": { "durationMS": 21.09280014038086, "detail": "Unity.TextMeshPro.cpp" } },
{ "pid": 1, "tid": 115, "ts": 212316.80297851562, "dur": 8172.100067138672, "ph": "X", "name": "HashCompilerInvocation", "args": { "durationMS": 8.172100067138672, "detail": "UnityEngine.CoreModule.cpp" } },
{ "pid": 1, "tid": 115, "ts": 220516.4031982422, "dur": 7169.400215148926, "ph": "X", "name": "HashCompilerInvocation", "args": { "durationMS": 7.169400215148926, "detail": "mscorlib2.cpp" } },
{ "pid": 1, "tid": 115, "ts": 227712.31079101562, "dur": 8881.8998336792, "ph": "X", "name": "HashCompilerInvocation", "args": { "durationMS": 8.8818998336792, "detail": "mscorlib8.cpp" } },
{ "pid": 1, "tid": 115, "ts": 236615.49377441406, "dur": 13490.09895324707, "ph": "X", "name": "HashCompilerInvocation", "args": { "durationMS": 13.49009895324707, "detail": "Generics8.cpp" } },
{ "pid": 1, "tid": 115, "ts": 250159.40856933594, "dur": 2387.5999450683594, "ph": "X", "name": "HashCompilerInvocation", "args": { "durationMS": 2.3875999450683594, "detail": "UnityEngine.UnityWebRequestModule.cpp" } },
{ "pid": 1, "tid": 115, "ts": 252573.8983154297, "dur": 1976.699948310852, "ph": "X", "name": "HashCompilerInvocation", "args": { "durationMS": 1.976699948310852, "detail": "Unity.2D.IK.Runtime.cpp" } },
{ "pid": 1, "tid": 115, "ts": 254572.60131835938, "dur": 1629.699945449829, "ph": "X", "name": "HashCompilerInvocation", "args": { "durationMS": 1.629699945449829, "detail": "UnityEngine.AnimationModule.cpp" } },
{ "pid": 1, "tid": 115, "ts": 256220.00122070312, "dur": 1189.2000436782837, "ph": "X", "name": "HashCompilerInvocation", "args": { "durationMS": 1.1892000436782837, "detail": "System_CodeGen.c" } },
{ "pid": 1, "tid": 115, "ts": 257433.7158203125, "dur": 1748.4999895095825, "ph": "X", "name": "HashCompilerInvocation", "args": { "durationMS": 1.7484999895095825, "detail": "UnityEngine.TextCoreModule_Attr.cpp" } },
{ "pid": 1, "tid": 115, "ts": 259211.3037109375, "dur": 2687.5, "ph": "X", "name": "HashCompilerInvocation", "args": { "durationMS": 2.6875, "detail": "UnityEngine.UnityWebRequestModule_Attr.cpp" } },
{ "pid": 1, "tid": 115, "ts": 261922.88208007812, "dur": 1258.7000131607056, "ph": "X", "name": "HashCompilerInvocation", "args": { "durationMS": 1.2587000131607056, "detail": "System_Attr.cpp" } },
{ "pid": 1, "tid": 115, "ts": 263201.7822265625, "dur": 1376.7000436782837, "ph": "X", "name": "HashCompilerInvocation", "args": { "durationMS": 1.3767000436782837, "detail": "UnityEngine.TextCoreModule_CodeGen.c" } },
{ "pid": 1, "tid": 115, "ts": 264600.6164550781, "dur": 10471.699714660645, "ph": "X", "name": "HashCompilerInvocation", "args": { "durationMS": 10.471699714660645, "detail": "UnityEngine.UIModule_CodeGen.c" } },
{ "pid": 1, "tid": 115, "ts": 275098.9990234375, "dur": 2428.9000034332275, "ph": "X", "name": "HashCompilerInvocation", "args": { "durationMS": 2.4289000034332275, "detail": "Mono.Security_CodeGen.c" } },
{ "pid": 1, "tid": 115, "ts": 277552.0935058594, "dur": 4764.900207519531, "ph": "X", "name": "HashCompilerInvocation", "args": { "durationMS": 4.764900207519531, "detail": "krait_signal_handler.c" } },
{ "pid": 1, "tid": 115, "ts": 282342.71240234375, "dur": 22815.59944152832, "ph": "X", "name": "HashCompilerInvocation", "args": { "durationMS": 22.81559944152832, "detail": "Il2CppGenericComDefinitions12.cpp" } },
{ "pid": 1, "tid": 120, "ph": "M", "name": "thread_name", "args": { "name": "" } },
{ "pid": 1, "tid": 120, "ts": 190862.89978027344, "dur": 22418.60008239746, "ph": "X", "name": "HashCompilerInvocation", "args": { "durationMS": 22.41860008239746, "detail": "GenericMethods1.cpp" } },
{ "pid": 1, "tid": 120, "ts": 213312.60681152344, "dur": 13247.099876403809, "ph": "X", "name": "HashCompilerInvocation", "args": { "durationMS": 13.247099876403809, "detail": "mscorlib13.cpp" } },
{ "pid": 1, "tid": 120, "ts": 226588.10424804688, "dur": 6812.79993057251, "ph": "X", "name": "HashCompilerInvocation", "args": { "durationMS": 6.81279993057251, "detail": "Generics.cpp" } },
{ "pid": 1, "tid": 120, "ts": 233438.69018554688, "dur": 30538.400650024414, "ph": "X", "name": "HashCompilerInvocation", "args": { "durationMS": 30.538400650024414, "detail": "mscorlib3.cpp" } },
{ "pid": 1, "tid": 120, "ts": 264004.5166015625, "dur": 1420.799970626831, "ph": "X", "name": "HashCompilerInvocation", "args": { "durationMS": 1.420799970626831, "detail": "UnityEngine.Physics2DModule.cpp" } },
{ "pid": 1, "tid": 120, "ts": 265447.6013183594, "dur": 7650.400161743164, "ph": "X", "name": "HashCompilerInvocation", "args": { "durationMS": 7.650400161743164, "detail": "gzwrite.c" } },
{ "pid": 1, "tid": 120, "ts": 273123.10791015625, "dur": 1775.6999731063843, "ph": "X", "name": "HashCompilerInvocation", "args": { "durationMS": 1.7756999731063843, "detail": "UnityEngine.InputLegacyModule_CodeGen.c" } },
{ "pid": 1, "tid": 120, "ts": 274936.6149902344, "dur": 5557.09981918335, "ph": "X", "name": "HashCompilerInvocation", "args": { "durationMS": 5.55709981918335, "detail": "Lump_libil2cpp_vm.cpp" } },
{ "pid": 1, "tid": 120, "ts": 280522.9187011719, "dur": 6371.200084686279, "ph": "X", "name": "HashCompilerInvocation", "args": { "durationMS": 6.371200084686279, "detail": "Lump_libil2cpp_gc.cpp" } },
{ "pid": 1, "tid": 120, "ts": 286924.2248535156, "dur": 4923.900127410889, "ph": "X", "name": "HashCompilerInvocation", "args": { "durationMS": 4.923900127410889, "detail": "Il2CppGenericComDefinitions15.cpp" } },
{ "pid": 1, "tid": 120, "ts": 291875.30517578125, "dur": 1991.7999505996704, "ph": "X", "name": "HashCompilerInvocation", "args": { "durationMS": 1.9917999505996704, "detail": "Il2CppGenericComDefinitions8.cpp" } },
{ "pid": 1, "tid": 110, "ph": "M", "name": "thread_name", "args": { "name": "" } },
{ "pid": 1, "tid": 110, "ts": 190867.70629882812, "dur": 32957.79800415039, "ph": "X", "name": "HashCompilerInvocation", "args": { "durationMS": 32.95779800415039, "detail": "Il2CppCCalculateTypeValues.cpp" } },
{ "pid": 1, "tid": 110, "ts": 223864.9139404297, "dur": 12651.700019836426, "ph": "X", "name": "HashCompilerInvocation", "args": { "durationMS": 12.651700019836426, "detail": "Generics3.cpp" } },
{ "pid": 1, "tid": 110, "ts": 236547.50061035156, "dur": 13635.99967956543, "ph": "X", "name": "HashCompilerInvocation", "args": { "durationMS": 13.63599967956543, "detail": "mscorlib11.cpp" } },
{ "pid": 1, "tid": 110, "ts": 250216.5985107422, "dur": 2549.999952316284, "ph": "X", "name": "HashCompilerInvocation", "args": { "durationMS": 2.549999952316284, "detail": "UnityEngine.CoreModule_CodeGen.c" } },
{ "pid": 1, "tid": 110, "ts": 252789.70336914062, "dur": 1896.9999551773071, "ph": "X", "name": "HashCompilerInvocation", "args": { "durationMS": 1.8969999551773071, "detail": "UnityEngine.UI_Attr.cpp" } },
{ "pid": 1, "tid": 110, "ts": 254724.30419921875, "dur": 1708.400011062622, "ph": "X", "name": "HashCompilerInvocation", "args": { "durationMS": 1.708400011062622, "detail": "UnityEngine.AndroidJNIModule_Attr.cpp" } },
{ "pid": 1, "tid": 110, "ts": 256449.67651367188, "dur": 1283.6999893188477, "ph": "X", "name": "HashCompilerInvocation", "args": { "durationMS": 1.2836999893188477, "detail": "Il2CppGenericMethodDefinitions.c" } },
{ "pid": 1, "tid": 110, "ts": 257761.5966796875, "dur": 1873.8000392913818, "ph": "X", "name": "HashCompilerInvocation", "args": { "durationMS": 1.8738000392913818, "detail": "UnityEngine.SharedInternalsModule_Attr.cpp" } },
{ "pid": 1, "tid": 110, "ts": 259659.39331054688, "dur": 3174.5998859405518, "ph": "X", "name": "HashCompilerInvocation", "args": { "durationMS": 3.1745998859405518, "detail": "UnityEngine.TextRenderingModule_Attr.cpp" } },
{ "pid": 1, "tid": 110, "ts": 262861.6943359375, "dur": 1326.69997215271, "ph": "X", "name": "HashCompilerInvocation", "args": { "durationMS": 1.32669997215271, "detail": "UnityEngine.IMGUIModule_CodeGen.c" } },
{ "pid": 1, "tid": 110, "ts": 264214.2028808594, "dur": 5934.299945831299, "ph": "X", "name": "HashCompilerInvocation", "args": { "durationMS": 5.934299945831299, "detail": "xamarin_getifaddrs.c" } },
{ "pid": 1, "tid": 110, "ts": 270192.4133300781, "dur": 2748.3999729156494, "ph": "X", "name": "HashCompilerInvocation", "args": { "durationMS": 2.7483999729156494, "detail": "System.Core_CodeGen.c" } },
{ "pid": 1, "tid": 110, "ts": 272969.6044921875, "dur": 2170.3999042510986, "ph": "X", "name": "HashCompilerInvocation", "args": { "durationMS": 2.1703999042510986, "detail": "inftrees.c" } },
{ "pid": 1, "tid": 110, "ts": 275165.22216796875, "dur": 2302.7000427246094, "ph": "X", "name": "HashCompilerInvocation", "args": { "durationMS": 2.3027000427246094, "detail": "UnityEngine.SpriteShapeModule.cpp" } },
{ "pid": 1, "tid": 110, "ts": 277495.30029296875, "dur": 2936.7001056671143, "ph": "X", "name": "HashCompilerInvocation", "args": { "durationMS": 2.9367001056671143, "detail": "UnityAdsStubs.cpp" } },
{ "pid": 1, "tid": 110, "ts": 280458.8928222656, "dur": 1617.5999641418457, "ph": "X", "name": "HashCompilerInvocation", "args": { "durationMS": 1.6175999641418457, "detail": "il2cpp-benchmark-support.cpp" } },
{ "pid": 1, "tid": 110, "ts": 282108.2763671875, "dur": 8126.999855041504, "ph": "X", "name": "HashCompilerInvocation", "args": { "durationMS": 8.126999855041504, "detail": "Il2CppGenericComDefinitions1.cpp" } },
{ "pid": 1, "tid": 110, "ts": 290259.8876953125, "dur": 1449.9000310897827, "ph": "X", "name": "HashCompilerInvocation", "args": { "durationMS": 1.4499000310897827, "detail": "Il2CppGenericComDefinitions18.cpp" } },
{ "pid": 1, "tid": 110, "ts": 291733.3984375, "dur": 2003.0999183654785, "ph": "X", "name": "HashCompilerInvocation", "args": { "durationMS": 2.0030999183654785, "detail": "Il2CppGenericComDefinitions6.cpp" } },
{ "pid": 1, "tid": 119, "ph": "M", "name": "thread_name", "args": { "name": "" } },
{ "pid": 1, "tid": 119, "ts": 190873.19946289062, "dur": 20844.200134277344, "ph": "X", "name": "HashCompilerInvocation", "args": { "durationMS": 20.844200134277344, "detail": "mscorlib9.cpp" } },
{ "pid": 1, "tid": 119, "ts": 212316.80297851562, "dur": 10078.200340270996, "ph": "X", "name": "HashCompilerInvocation", "args": { "durationMS": 10.078200340270996, "detail": "UnityEngine.UI.cpp" } },
{ "pid": 1, "tid": 119, "ts": 222422.50061035156, "dur": 7457.300186157227, "ph": "X", "name": "HashCompilerInvocation", "args": { "durationMS": 7.457300186157227, "detail": "mscorlib5.cpp" } },
{ "pid": 1, "tid": 119, "ts": 229905.60913085938, "dur": 11153.200149536133, "ph": "X", "name": "HashCompilerInvocation", "args": { "durationMS": 11.153200149536133, "detail": "GenericMethods.cpp" } },
{ "pid": 1, "tid": 119, "ts": 241089.00451660156, "dur": 12942.099571228027, "ph": "X", "name": "HashCompilerInvocation", "args": { "durationMS": 12.942099571228027, "detail": "Unity.TextMeshPro5.cpp" } },
{ "pid": 1, "tid": 119, "ts": 254063.49182128906, "dur": 1636.6000175476074, "ph": "X", "name": "HashCompilerInvocation", "args": { "durationMS": 1.6366000175476074, "detail": "UnresolvedVirtualCallStubs.cpp" } },
{ "pid": 1, "tid": 119, "ts": 255722.59521484375, "dur": 1171.0000038146973, "ph": "X", "name": "HashCompilerInvocation", "args": { "durationMS": 1.1710000038146973, "detail": "UnityEngine.TextRenderingModule.cpp" } },
{ "pid": 1, "tid": 119, "ts": 256919.189453125, "dur": 2516.5998935699463, "ph": "X", "name": "HashCompilerInvocation", "args": { "durationMS": 2.5165998935699463, "detail": "UnityEngine.InputLegacyModule.cpp" } },
{ "pid": 1, "tid": 119, "ts": 259461.70043945312, "dur": 2749.799966812134, "ph": "X", "name": "HashCompilerInvocation", "args": { "durationMS": 2.749799966812134, "detail": "UnityEngine.AudioModule.cpp" } },
{ "pid": 1, "tid": 119, "ts": 262234.8937988281, "dur": 1643.9000368118286, "ph": "X", "name": "HashCompilerInvocation", "args": { "durationMS": 1.6439000368118286, "detail": "System.Core_Attr.cpp" } },
{ "pid": 1, "tid": 119, "ts": 263903.99169921875, "dur": 1452.4999856948853, "ph": "X", "name": "HashCompilerInvocation", "args": { "durationMS": 1.4524999856948853, "detail": "Mono.Security_Attr.cpp" } },
{ "pid": 1, "tid": 119, "ts": 265391.29638671875, "dur": 10104.900360107422, "ph": "X", "name": "HashCompilerInvocation", "args": { "durationMS": 10.104900360107422, "detail": "Lump_libil2cpp_os.cpp" } },
{ "pid": 1, "tid": 119, "ts": 275521.30126953125, "dur": 2461.6000652313232, "ph": "X", "name": "HashCompilerInvocation", "args": { "durationMS": 2.4616000652313232, "detail": "uncompr.c" } },
{ "pid": 1, "tid": 119, "ts": 278005.9814453125, "dur": 2627.000093460083, "ph": "X", "name": "HashCompilerInvocation", "args": { "durationMS": 2.627000093460083, "detail": "System.Xml_CodeGen.c" } },
{ "pid": 1, "tid": 119, "ts": 280663.9099121094, "dur": 1496.2999820709229, "ph": "X", "name": "HashCompilerInvocation", "args": { "durationMS": 1.4962999820709229, "detail": "UnityEngine.SpriteShapeModule_CodeGen.c" } },
{ "pid": 1, "tid": 119, "ts": 282182.80029296875, "dur": 8567.500114440918, "ph": "X", "name": "HashCompilerInvocation", "args": { "durationMS": 8.567500114440918, "detail": "Il2CppGenericComDefinitions10.cpp" } },
{ "pid": 1, "tid": 119, "ts": 290780.21240234375, "dur": 1403.5999774932861, "ph": "X", "name": "HashCompilerInvocation", "args": { "durationMS": 1.4035999774932861, "detail": "Il2CppGenericComDefinitions2.cpp" } },
{ "pid": 1, "tid": 119, "ts": 292206.2072753906, "dur": 1657.8999757766724, "ph": "X", "name": "HashCompilerInvocation", "args": { "durationMS": 1.6578999757766724, "detail": "Il2CppGenericComDefinitions9.cpp" } },
{ "pid": 1, "tid": 114, "ph": "M", "name": "thread_name", "args": { "name": "" } },
{ "pid": 1, "tid": 114, "ts": 190875.1983642578, "dur": 27466.70150756836, "ph": "X", "name": "HashCompilerInvocation", "args": { "durationMS": 27.46670150756836, "detail": "Generics4.cpp" } },
{ "pid": 1, "tid": 114, "ts": 218388.5040283203, "dur": 13516.599655151367, "ph": "X", "name": "HashCompilerInvocation", "args": { "durationMS": 13.516599655151367, "detail": "Generics5.cpp" } },
{ "pid": 1, "tid": 114, "ts": 231932.4951171875, "dur": 7240.900039672852, "ph": "X", "name": "HashCompilerInvocation", "args": { "durationMS": 7.240900039672852, "detail": "mscorlib12.cpp" } },
{ "pid": 1, "tid": 114, "ts": 239200.10375976562, "dur": 11572.699546813965, "ph": "X", "name": "HashCompilerInvocation", "args": { "durationMS": 11.572699546813965, "detail": "Assembly-CSharp.cpp" } },
{ "pid": 1, "tid": 114, "ts": 250798.9959716797, "dur": 1976.3000011444092, "ph": "X", "name": "HashCompilerInvocation", "args": { "durationMS": 1.9763000011444092, "detail": "Unity.TextMeshPro_CodeGen.c" } },
{ "pid": 1, "tid": 114, "ts": 252800.99487304688, "dur": 1826.5000581741333, "ph": "X", "name": "HashCompilerInvocation", "args": { "durationMS": 1.8265000581741333, "detail": "Il2CppGenericAdjustorThunkTable.cpp" } },
{ "pid": 1, "tid": 114, "ts": 254650.00915527344, "dur": 1803.7999868392944, "ph": "X", "name": "HashCompilerInvocation", "args": { "durationMS": 1.8037999868392944, "detail": "UnityEngine.UIModule.cpp" } },
{ "pid": 1, "tid": 114, "ts": 256480.98754882812, "dur": 1982.300043106079, "ph": "X", "name": "HashCompilerInvocation", "args": { "durationMS": 1.982300043106079, "detail": "UnityEngine.AnimationModule_Attr.cpp" } },
{ "pid": 1, "tid": 114, "ts": 258492.00439453125, "dur": 1447.100043296814, "ph": "X", "name": "HashCompilerInvocation", "args": { "durationMS": 1.447100043296814, "detail": "UnityEngine.UIModule_Attr.cpp" } },
{ "pid": 1, "tid": 114, "ts": 259961.48681640625, "dur": 1754.09996509552, "ph": "X", "name": "HashCompilerInvocation", "args": { "durationMS": 1.75409996509552, "detail": "UnityEngine.PhysicsModule_Attr.cpp" } },
{ "pid": 1, "tid": 114, "ts": 261737.3046875, "dur": 1376.7999410629272, "ph": "X", "name": "HashCompilerInvocation", "args": { "durationMS": 1.3767999410629272, "detail": "UnityEngine.GridModule_Attr.cpp" } },
{ "pid": 1, "tid": 114, "ts": 263136.41357421875, "dur": 1353.8000583648682, "ph": "X", "name": "HashCompilerInvocation", "args": { "durationMS": 1.3538000583648682, "detail": "System.Configuration_Attr.cpp" } },
{ "pid": 1, "tid": 114, "ts": 264512.1154785156, "dur": 7622.700214385986, "ph": "X", "name": "HashCompilerInvocation", "args": { "durationMS": 7.622700214385986, "detail": "Unity.2D.IK.Runtime_CodeGen.c" } },
{ "pid": 1, "tid": 114, "ts": 272160.21728515625, "dur": 1494.6000576019287, "ph": "X", "name": "HashCompilerInvocation", "args": { "durationMS": 1.4946000576019287, "detail": "UnityEngine.SharedInternalsModule_CodeGen.c" } },
{ "pid": 1, "tid": 114, "ts": 273676.7883300781, "dur": 1827.4999856948853, "ph": "X", "name": "HashCompilerInvocation", "args": { "durationMS": 1.8274999856948853, "detail": "System.Xml.cpp" } },
{ "pid": 1, "tid": 114, "ts": 275536.31591796875, "dur": 2193.5999393463135, "ph": "X", "name": "HashCompilerInvocation", "args": { "durationMS": 2.1935999393463135, "detail": "UnityEngine.Physics2DModule_CodeGen.c" } },
{ "pid": 1, "tid": 114, "ts": 277762.6037597656, "dur": 13292.3002243042, "ph": "X", "name": "HashCompilerInvocation", "args": { "durationMS": 13.2923002243042, "detail": "Il2CppMetadataRegistration.c" } },
{ "pid": 1, "tid": 114, "ts": 291082.1228027344, "dur": 1886.8000507354736, "ph": "X", "name": "HashCompilerInvocation", "args": { "durationMS": 1.8868000507354736, "detail": "Il2CppGenericComDefinitions20.cpp" } },
{ "pid": 1, "tid": 114, "ts": 293002.5939941406, "dur": 1066.9000148773193, "ph": "X", "name": "HashCompilerInvocation", "args": { "durationMS": 1.0669000148773193, "detail": "il2cpp-runtime-stats.cpp" } },
{ "pid": 1, "tid": 223, "ph": "M", "name": "thread_name", "args": { "name": "" } },
{ "pid": 1, "tid": 223, "ts": 244847.900390625, "dur": 5263.599872589111, "ph": "X", "name": "HeaderFileHashProvider.HashForAllHeaderFilesReachableByFilesIn", "args": { "durationMS": 5.263599872589111, "detail": "C:\\Program Files\\Unity\\Hub\\Editor\\2020.3.6f1\\Editor\\Data\\il2cpp\\external\\baselib\\Include" } },
{ "pid": 1, "tid": 151, "ph": "M", "name": "thread_name", "args": { "name": "" } },
{ "pid": 1, "tid": 151, "ts": 278308.28857421875, "dur": 930.9999942779541, "ph": "X", "name": "HeaderFileHashProvider.HashForAllHeaderFilesReachableByFilesIn", "args": { "durationMS": 0.9309999942779541, "detail": "C:\\Program Files\\Unity\\Hub\\Editor\\2020.3.6f1\\Editor\\Data\\il2cpp\\libil2cpp" } },
{ "pid": 1, "tid": 162, "ph": "M", "name": "thread_name", "args": { "name": "" } },
{ "pid": 1, "tid": 162, "ts": 312804.8095703125, "dur": 1173473.14453125, "ph": "X", "name": "Compile", "args": { "durationMS": 1173.47314453125, "detail": "Assembly-CSharp.cpp" } }
],
"meta_datetime": "11/14/2022 20:23:07",
"meta_command_line": "\"C:\\Program Files\\Unity\\Hub\\Editor\\2020.3.6f1\\Editor\\Data\\il2cpp\\build\\deploy\\netcoreapp3.1\\il2cpp.dll\" --compile-cpp --libil2cpp-static --platform=Android --architecture=ARM64 --configuration=Release --outputpath=C:\\Users\\MSI\\Documents\\GitHub\\Sample\\Engine\\Library\\Il2cppBuildCache\\Android\\arm64-v8a\\Native\\arm64-v8a\\libil2cpp.so --cachedirectory=C:\\Users\\MSI\\Documents\\GitHub\\Sample\\Engine\\Assets\\..\\Library\\il2cpp_android_arm64-v8a/il2cpp_cache \"--additional-include-directories=C:/Program Files/Unity/Hub/Editor/2020.3.6f1/Editor/Data/PlaybackEngines/AndroidPlayer/Tools\\bdwgc/include\" \"--additional-include-directories=C:/Program Files/Unity/Hub/Editor/2020.3.6f1/Editor/Data/PlaybackEngines/AndroidPlayer/Tools\\libil2cpp/include\" \"--baselib-directory=C:/Program Files/Unity/Hub/Editor/2020.3.6f1/Editor/Data/PlaybackEngines/AndroidPlayer\\Variations\\il2cpp\\Release\\StaticLibs\\arm64-v8a\" --avoid-dynamic-library-copy \"--tool-chain-path=C:/Program Files/Unity/Hub/Editor/2020.3.6f1/Editor/Data/PlaybackEngines/AndroidPlayer/NDK\" --incremental-g-c-time-slice=3 --profiler-report \"--map-file-parser=C:/Program Files/Unity/Hub/Editor/2020.3.6f1/Editor/Data/Tools/MapFileParser/MapFileParser.exe\" --generatedcppdir=C:/Users/MSI/Documents/GitHub/Sample/Engine/Library/Il2cppBuildCache/Android/armeabi-v7a/il2cppOutput --dotnetprofile=unityaot",
"meta_command_line_args": "C:\\Program Files\\Unity\\Hub\\Editor\\2020.3.6f1\\Editor\\Data\\il2cpp\\build\\deploy\\netcoreapp3.1\\il2cpp.dll --compile-cpp --libil2cpp-static --platform=Android --architecture=ARM64 --configuration=Release --outputpath=C:\\Users\\MSI\\Documents\\GitHub\\Sample\\Engine\\Library\\Il2cppBuildCache\\Android\\arm64-v8a\\Native\\arm64-v8a\\libil2cpp.so --cachedirectory=C:\\Users\\MSI\\Documents\\GitHub\\Sample\\Engine\\Assets\\..\\Library\\il2cpp_android_arm64-v8a/il2cpp_cache --additional-include-directories=C:/Program Files/Unity/Hub/Editor/2020.3.6f1/Editor/Data/PlaybackEngines/AndroidPlayer/Tools\\bdwgc/include --additional-include-directories=C:/Program Files/Unity/Hub/Editor/2020.3.6f1/Editor/Data/PlaybackEngines/AndroidPlayer/Tools\\libil2cpp/include --baselib-directory=C:/Program Files/Unity/Hub/Editor/2020.3.6f1/Editor/Data/PlaybackEngines/AndroidPlayer\\Variations\\il2cpp\\Release\\StaticLibs\\arm64-v8a --avoid-dynamic-library-copy --tool-chain-path=C:/Program Files/Unity/Hub/Editor/2020.3.6f1/Editor/Data/PlaybackEngines/AndroidPlayer/NDK --incremental-g-c-time-slice=3 --profiler-report --map-file-parser=C:/Program Files/Unity/Hub/Editor/2020.3.6f1/Editor/Data/Tools/MapFileParser/MapFileParser.exe --generatedcppdir=C:/Users/MSI/Documents/GitHub/Sample/Engine/Library/Il2cppBuildCache/Android/armeabi-v7a/il2cppOutput --dotnetprofile=unityaot",
"meta_user_name": "MSI",
"meta_os_version": "Microsoft Windows NT 6.2.9200.0",
"meta_cpu_count": "12"}
